[
  {
    "identifier": "1902-05-22-10",
    "shortTitle": "Straffeloven 1902",
    "mirror": "2005-05-20-28"
  },
  {
    "identifier": "1980-06-13-24",
    "shortTitle": "Ligningsloven",
    "mirror": ""
  },
  {
    "identifier": "1997-05-23-31",
    "shortTitle": "Eierseksjonsloven",
    "mirror": ""
  },
  {
    "identifier": "1915-08-13-6",
    "shortTitle": "Tvistemålsloven",
    "mirror": ""
  },
  {
    "identifier": "1975-05-30-20",
    "shortTitle": "Tomtefestelov",
    "mirror": ""
  },
  {
    "identifier": "1979-12-21-77",
    "shortTitle": "Jordskiftelov",
    "mirror": ""
  },
  {
    "identifier": "1985-06-14-77",
    "shortTitle": "Plan- og bygningslov",
    "mirror": ""
  }
]
